README
setup.py
src/SpiffGtkWidgets/__init__.py
src/SpiffGtkWidgets/color.py
src/SpiffGtkWidgets.egg-info/PKG-INFO
src/SpiffGtkWidgets.egg-info/SOURCES.txt
src/SpiffGtkWidgets.egg-info/dependency_links.txt
src/SpiffGtkWidgets.egg-info/top_level.txt
src/SpiffGtkWidgets/Calendar/Calendar.py
src/SpiffGtkWidgets/Calendar/CanvasDay.py
src/SpiffGtkWidgets/Calendar/CanvasDayRange.py
src/SpiffGtkWidgets/Calendar/CanvasEvent.py
src/SpiffGtkWidgets/Calendar/CanvasEventView.py
src/SpiffGtkWidgets/Calendar/CanvasGrid.py
src/SpiffGtkWidgets/Calendar/CanvasHEventView.py
src/SpiffGtkWidgets/Calendar/CanvasMagnetTable.py
src/SpiffGtkWidgets/Calendar/CanvasRectangle.py
src/SpiffGtkWidgets/Calendar/CanvasTable.py
src/SpiffGtkWidgets/Calendar/CanvasTimeline.py
src/SpiffGtkWidgets/Calendar/CanvasVEventView.py
src/SpiffGtkWidgets/Calendar/Event.py
src/SpiffGtkWidgets/Calendar/Matrix.py
src/SpiffGtkWidgets/Calendar/Model.py
src/SpiffGtkWidgets/Calendar/MyCalendar.py
src/SpiffGtkWidgets/Calendar/TableLayout.py
src/SpiffGtkWidgets/Calendar/__init__.py
src/SpiffGtkWidgets/Calendar/util.py
src/SpiffGtkWidgets/TextEditor/Annotation.py
src/SpiffGtkWidgets/TextEditor/Layout.py
src/SpiffGtkWidgets/TextEditor/LayoutBox.py
src/SpiffGtkWidgets/TextEditor/TextBuffer.py
src/SpiffGtkWidgets/TextEditor/TextEditor.py
src/SpiffGtkWidgets/TextEditor/UndoApplyTag.py
src/SpiffGtkWidgets/TextEditor/UndoCollection.py
src/SpiffGtkWidgets/TextEditor/UndoDeleteText.py
src/SpiffGtkWidgets/TextEditor/UndoInsertText.py
src/SpiffGtkWidgets/TextEditor/UndoRemoveTag.py
src/SpiffGtkWidgets/TextEditor/Undoable.py
src/SpiffGtkWidgets/TextEditor/__init__.py
src/SpiffGtkWidgets/TextEditor/Features/Feature.py
src/SpiffGtkWidgets/TextEditor/Features/ListIndent.py
src/SpiffGtkWidgets/TextEditor/Features/SpellChecking.py
src/SpiffGtkWidgets/TextEditor/Features/__init__.py