Metadata-Version: 1.0
Name: SpiffGtkWidgets
Version: 0.2.0
Summary: A collection of useful Gtk widgets
Home-page: http://code.google.com/p/spiff-gtkwidgets/
Author: Samuel Abels
Author-email: cheeseshop.python.org@debain.org
License: GPLv2
Keywords: spiff gtk widgets textview annotations calendar
Platform: UNKNOWN
Classifier: Development Status :: 5 - Production/Stable
Classifier: Intended Audience :: Developers
Classifier: License :: OSI Approved :: GNU General Public License (GPL)
Classifier: Programming Language :: Python
Classifier: Topic :: Security
Classifier: Topic :: Software Development :: Libraries
Classifier: Topic :: Software Development :: Libraries :: Python Modules
